scrapemm/__init__.py
scrapemm/retrieval.py
scrapemm/secrets.py
scrapemm/util.py
scrapemm/common/__init__.py
scrapemm/common/exceptions.py
scrapemm/common/scraping_response.py
scrapemm/download/__init__.py
scrapemm/download/common.py
scrapemm/download/images.py
scrapemm/download/media.py
scrapemm/download/requests.py
scrapemm/download/util.py
scrapemm/download/videos.py
scrapemm/integrations/__init__.py
scrapemm/integrations/archive_org.py
scrapemm/integrations/base.py
scrapemm/integrations/bluesky.py
scrapemm/integrations/decodo.py
scrapemm/integrations/fb.py
scrapemm/integrations/instagram.py
scrapemm/integrations/perma_cc.py
scrapemm/integrations/telegram.py
scrapemm/integrations/tiktok.py
scrapemm/integrations/x.py
scrapemm/integrations/youtube.py
scrapemm/integrations/ytdlp.py
scrapemm/integrations/firecrawl/__init__.py
scrapemm/integrations/firecrawl/firecrawl.py
scrapemm/integrations/firecrawl/no_bot_domains.txt
scrapemm-0.5.5.dist-info/licenses/LICENSE
scrapemm-0.5.5.dist-info/METADATA
scrapemm-0.5.5.dist-info/WHEEL
scrapemm-0.5.5.dist-info/top_level.txt
scrapemm-0.5.5.dist-info/RECORD
