Metadata-Version: 2.4
Name: scrapeMM
Version: 0.5.5
Summary: Flexible multimodal scraper for social media and the open web.
Author-email: Mark Rothermel <mark.rothermel@tu-darmstadt.de>
License-Expression: Apache-2.0
Project-URL: Homepage, https://github.com/multimodal-ai-lab/scrapeMM
Project-URL: Issues, https://github.com/multimodal-ai-lab/scrapeMM
Requires-Python: >=3.10
License-File: LICENSE
Requires-Dist: ezmm
Requires-Dist: telethon
Requires-Dist: tweepy
Requires-Dist: markdownify
Requires-Dist: platformdirs
Requires-Dist: PyYAML
Requires-Dist: atproto
Requires-Dist: TikTokResearchApi
Requires-Dist: yt-dlp
Requires-Dist: cryptography
Requires-Dist: firecrawl-py
Requires-Dist: playwright
Dynamic: license-file
